LICENSE
MANIFEST.in
README.rst
setup.py
docs/HISTORY.rst
docs/Makefile
docs/clamav.txt
docs/conf.py
docs/configuration.rst
docs/index.rst
docs/installation.rst
docs/make.bat
docs/nkp_logo.png
docs/notes.txt
docs/python-clamav.txt
docs/rabbitmq.txt
docs/requirements.rst
docs/requirements.txt
docs/usage-keywords.rst
docs/usage.rst
edeposit/__init__.py
edeposit.amqp.antivir.egg-info/PKG-INFO
edeposit.amqp.antivir.egg-info/SOURCES.txt
edeposit.amqp.antivir.egg-info/dependency_links.txt
edeposit.amqp.antivir.egg-info/namespace_packages.txt
edeposit.amqp.antivir.egg-info/not-zip-safe
edeposit.amqp.antivir.egg-info/requires.txt
edeposit.amqp.antivir.egg-info/top_level.txt
edeposit/amqp/__init__.py
edeposit/amqp/antivir/__init__.py
edeposit/amqp/antivir/amqpav.py
edeposit/amqp/antivir/settings.py
edeposit/amqp/antivir/tests/__init__.py
edeposit/amqp/antivir/tests/inspector.py
edeposit/amqp/antivir/tests/variables.py
examples/avclient.py
examples/avlibclient.py
examples/avlibserver.py
examples/avservice.py
examples/clamav.py
examples/eicar
tests/test.txt