Metadata-Version: 1.1
Name: edeposit.amqp.antivir
Version: 0.1-alpha
Summary: E-Deposit module for RabbitMQ antivirus
Home-page: https://github.com/jstavel/edeposit.amqp.antivir/
Author: Edeposit team
Author-email: edeposit@email.cz
License: GPL2+
Platform: UNKNOWN
Classifier: Programming Language :: Python :: 2.7
Classifier: Development Status :: 3 - Alpha
Classifier: License :: OSI Approved :: GNU General Public License v2 or later (GPLv2+)
Classifier: Topic :: Software Development :: Libraries :: Python Modules
